README
pymongo_frisk.py
setup.py
PyMongo_Frisk.egg-info/PKG-INFO
PyMongo_Frisk.egg-info/SOURCES.txt
PyMongo_Frisk.egg-info/dependency_links.txt
PyMongo_Frisk.egg-info/requires.txt
PyMongo_Frisk.egg-info/top_level.txt