Metadata-Version: 1.0
Name: PyMongo-Frisk
Version: 0.0.4
Summary: Wrapper for PyMongo Connection that offers additional application level monitoring. When connecting to multiple MongoDB servers, allows you to verify connectivity to MongoDB slave servers.
Home-page: http://www.point2.com/
Author: Brian Richardson & James Townley
Author-email: jtownley@point2.com
License: Release under Apache-BSD style license
Platform: any
Classifier: Development Status :: 4 - Beta
Classifier: License :: OSI Approved :: Apache Software License
Classifier: License :: OSI Approved :: BSD License
Classifier: Natural Language :: English
Classifier: Programming Language :: Python :: 2.6
Classifier: Programming Language :: Python :: 2.7
Classifier: Topic :: Utilities
